bitcaviar_plus/__init__.py
bitcaviar_plus/block.py
bitcaviar_plus/block_structure.py
bitcaviar_plus/errors.py
bitcaviar_plus/helpers.py
bitcaviar_plus-0.0.2.dist-info/LICENSE.md
bitcaviar_plus-0.0.2.dist-info/METADATA
bitcaviar_plus-0.0.2.dist-info/WHEEL
bitcaviar_plus-0.0.2.dist-info/top_level.txt
bitcaviar_plus-0.0.2.dist-info/RECORD
