Metadata-Version: 2.1
Name: bitcaviar-plus
Version: 0.0.2
Summary: A Bitcoin blockchain parser written in Python
Home-page: https://github.com/denniscm190/bitcaviar-plus
Author: Dennis Concepcion Martin
Author-email: dennisconcepcionmartin@gmail.com
License: UNKNOWN
Project-URL: Bug Tracker, https://github.com/denniscm190/bitcaviar-plus/issues
Platform: UNKNOWN
Classifier: Programming Language :: Python :: 3
Classifier: License :: OSI Approved :: MIT License
Classifier: Operating System :: OS Independent
Requires-Python: >=3.8
License-File: LICENSE.md
